<?xml version="1.0" encoding="utf-8"?>
<products>
  <product name="TYLENOL COLD MULTI-SYMPTOM DAYTIME" price="1010.81" buyer="Sandra Riley" />
  <product name="Butalbital, Aspirin and Caffeine" price="1010.98" buyer="Clarence Fowler" />
  <product name="SEPHORA Acne-Fighting Mattifying Moisturizer" price="1019.28" buyer="Emily Parker" />
  <product name="CVS Therapeutic Menthol Pain Reliever" price="1033.42" buyer="Anna Parker" />
  <product name="Aspen" price="1046.46" buyer="Amanda Frazier" />
  <product name="Ringers" price="1054.37" buyer="Diana Harvey" />
  <product name="Acetic Acid" price="1060.43" buyer="Sarah Day" />
  <product name="LBEL Couleur Luxe Rouge Amplifier XP amplifying SPF 15" price="1069.43" buyer=" Baker" />
  <product name="Growing Pains" price="1077.37" buyer="Chris Mitchell" />
  <product name="up and up temporary minor arthritis pain relief" price="1085.78" buyer="Jennifer Riley" />
  <product name="Ibuprofen" price="1088.04" buyer="Anna Parker" />
  <product name="XANTHIUM STRUMARIUM VAR CANADENSE POLLEN" price="1091.38" buyer=" Schmidt" />
  <product name="ESIKA 3-IN-1 PRO MAKE UP FOUNDATION SPF 20 BASE DE MAQUILLAJE PARA ROSTRO 3-EN-1 PRO FPS 20" price="1097.60" buyer="Betty Ward" />
  <product name="Head and Shoulders Conditioner" price="1099.59" buyer="Sarah Day" />
  <product name="smart sense nighttime cold and flu relief" price="1101.77" buyer="Thomas Snyder" />
  <product name="PREMIER VALUE ALLERGY" price="1127.61" buyer=" Thompson" />
  <product name="Lorazepam" price="1134.96" buyer=" Lawson" />
  <product name="Laser Block 100" price="1135.43" buyer="Fred Barnes" />
  <product name="Pollens - Trees, Birch Mix" price="1153.54" buyer="Paula Hill" />
  <product name="Baza Antifungal" price="1162.34" buyer="Doris Cook" />
  <product name="Americaine" price="1165.75" buyer=" Bennett" />
  <product name="Benazepril Hydrochloride and Hydrochlorothiazide" price="1187.27" buyer="Amanda Frazier" />
  <product name="Topical 60 Sec Sodium Fluoride" price="1228.84" buyer="Gary Stevens" />
  <product name="Oxygen" price="1242.92" buyer="Doris Cook" />
  <product name="Ondansetron" price="1249.76" buyer="Jeremy Woods" />
  <product name="XtraCare Foam Antibacterial Hand Wash" price="1251.97" buyer=" Baker" />
  <product name="Topex" price="1258.49" buyer="Joshua Murray" />
  <product name="SUMATRIPTAN SUCCINATE" price="1265.94" buyer="Patricia Fuller" />
  <product name="Prednisone" price="1285.99" buyer="Arthur Reynolds" />
  <product name="DIVALPROEX SODIUM" price="1287.03" buyer=" Bennett" />
  <product name="VITALUMIERE AQUA" price="1293.09" buyer="Doris Cook" />
  <product name="MEDI-FIRST Non-Aspirin" price="1301.28" buyer="Kathy Gilbert" />
  <product name="Cefadroxil" price="1302.20" buyer=" Baker" />
  <product name="Zonisamide" price="1305.41" buyer="Jacqueline Perez" />
  <product name="Ibuprofen" price="1305.96" buyer=" Mitchell" />
  <product name="Hydralazine Hydrochloride" price="1309.72" buyer="Jonathan Rodriguez" />
  <product name="Fosphenytoin Sodium" price="1334.06" buyer="Anna Parker" />
  <product name="Archangelica Eucalyptus" price="1334.91" buyer="Fred Barnes" />
  <product name="Labetalol Hydrochloride" price="1345.11" buyer="Bonnie Fox" />
  <product name="MEDICATED DANDRUFF" price="1351.02" buyer="Fred Allen" />
  <product name="PCA SKIN ACNE" price="1356.22" buyer="Brandon Fuller" />
  <product name="EMEND" price="1365.51" buyer=" Lawson" />
  <product name="Finasteride" price="1374.01" buyer="Anna Parker" />
  <product name="Nevirapine" price="1374.72" buyer="Emily Parker" />
  <product name="Warfarin Sodium" price="1379.79" buyer="Jacqueline Perez" />
  <product name="Fair Foundation SPF 15" price="1394.24" buyer=" Cunningham" />
  <product name="Metoprolol Tartrate" price="1405.74" buyer="Carl Daniels" />
  <product name="Triamterene and Hydrochlorothiazide" price="1416.59" buyer="Jacqueline Perez" />
  <product name="Etodolac" price="1443.13" buyer=" Bennett" />
  <product name="smart sense nicotine" price="1444.12" buyer="Carl Daniels" />
  <product name="Amitriptyline Hydrochloride" price="1453.96" buyer="Diana Harvey" />
  <product name="Gilotrif" price="1454.77" buyer="Brenda Howell" />
  <product name="Treatment Set TS336667" price="1466.47" buyer="Nicole Harris" />
  <product name="GEMCITABINE" price="1468.11" buyer="Patricia Fuller" />
  <product name="Glycopyrrolate" price="1471.43" buyer="Gloria Alexander" />
  <product name="cough and sore throat" price="1482.68" buyer="Betty Lawson" />
  <product name="Etoposide" price="1483.96" buyer="Jeremy Woods" />
  <product name="Alcohol Free Antiseptic" price="1486.07" buyer="Patricia Fuller" />
</products>